consistency_model/__init__.py
consistency_model/admin.py
consistency_model/models.py
consistency_model/settings.py
consistency_model/tools.py
consistency_model/management/commands/consistency_model_check.py
consistency_model/management/commands/consistency_model_monitoring.py
consistency_model/migrations/0001_initial.py
consistency_model/migrations/__init__.py
django_consistency_model-0.1.1.dist-info/LICENSE.md
django_consistency_model-0.1.1.dist-info/METADATA
django_consistency_model-0.1.1.dist-info/WHEEL
django_consistency_model-0.1.1.dist-info/top_level.txt
django_consistency_model-0.1.1.dist-info/RECORD
